<?xml version="1.0" encoding="UTF-8" standalone="no"?>
<level version="1.4">
    <entities>
        <group x="0" y="0">
            <entity name="block" x="0.0" y="0.0"/>
            <entity name="block" x="1.0" y="0.0"/>
            <entity name="block" x="2.0" y="0.0"/>
            <entity name="block" x="3.0" y="0.0"/>
            <entity name="block" x="4.0" y="0.0"/>
            <entity name="block" x="5.0" y="0.0"/>
            <entity name="save" x="5.0" y="2.0"/>
            <entity name="block" x="6.0" y="0.0"/>
            <entity name="block" x="7.0" y="0.0"/>
            <entity name="block" x="8.0" y="0.0"/>
            <entity name="block" x="9.0" y="0.0"/>
            <entity name="block" x="10.0" y="0.0"/>
            <entity name="block" x="11.0" y="0.0"/>
            <entity name="block" x="12.0" y="0.0"/>
            <entity name="spike0" x="10.0" y="10.0"/>
            <entity name="platform" x="30.092472" y="3.0"/>
            <entity name="block" x="4.0" y="6.0"/>
            <entity name="block" x="5.0" y="6.0"/>
            <entity name="block" x="6.0" y="6.0"/>
            <entity name="yellowstar.screen1.trigger3" x="7.0" y="2.0"/>
            <entity name="spike90" x="3.0" y="3.0"/>
            <entity name="spike90" x="9.0" y="3.0"/>
        </group>
    </entities>
</level>
